color_mixer/__init__.py
color_mixer/color_core.py
color_mixer/estructuras.py
color_mixer/inventario_manager.py
color_mixer/visual_exports.py
color_mixer-0.0.3.dist-info/licenses/LICENCE
color_mixer-0.0.3.dist-info/METADATA
color_mixer-0.0.3.dist-info/WHEEL
color_mixer-0.0.3.dist-info/top_level.txt
color_mixer-0.0.3.dist-info/RECORD
