Metadata-Version: 2.4
Name: color_mixer
Version: 0.0.3
Summary: Paquete de utilidades para obtener los formatos PRONOM de un archivo
Home-page: https://github.com/armando-777/PG2_PRACTICA_7_ColorMixer
Author: Armando Clemente Isla
Author-email: armandoclemente.sis24ch@tecba.edu.bo
License: MIT
Classifier: Intended Audience :: Developers
Classifier: Programming Language :: Python
Classifier: Topic :: Software Development
Requires-Python: >=3.7
License-File: LICENCE
Dynamic: license-file
